{"nodes": [{"id": "backend_references_sn_reid_torchreid_models_mlfn_py", "label": "mlfn.py", "file_type": "code", "source_file": "backend/references/sn-reid/torchreid/models/mlfn.py", "source_location": "L1"}, {"id": "mlfn_mlfnblock", "label": "MLFNBlock", "file_type": "code", "source_file": "backend/references/sn-reid/torchreid/models/mlfn.py", "source_location": "L16"}, {"id": "mlfn_mlfnblock_init", "label": ".__init__()", "file_type": "code", "source_file": "backend/references/sn-reid/torchreid/models/mlfn.py", "source_location": "L18"}, {"id": "mlfn_mlfnblock_forward", "label": ".forward()", "file_type": "code", "source_file": "backend/references/sn-reid/torchreid/models/mlfn.py", "source_location": "L64"}, {"id": "mlfn_mlfn", "label": "MLFN", "file_type": "code", "source_file": "backend/references/sn-reid/torchreid/models/mlfn.py", "source_location": "L98"}, {"id": "mlfn_mlfn_init", "label": ".__init__()", "file_type": "code", "source_file": "backend/references/sn-reid/torchreid/models/mlfn.py", "source_location": "L109"}, {"id": "mlfn_mlfn_init_params", "label": ".init_params()", "file_type": "code", "source_file": "backend/references/sn-reid/torchreid/models/mlfn.py", "source_location": "L196"}, {"id": "mlfn_mlfn_forward", "label": ".forward()", "file_type": "code", "source_file": "backend/references/sn-reid/torchreid/models/mlfn.py", "source_location": "L212"}, {"id": "mlfn_init_pretrained_weights", "label": "init_pretrained_weights()", "file_type": "code", "source_file": "backend/references/sn-reid/torchreid/models/mlfn.py", "source_location": "L244"}, {"id": "mlfn_rationale_99", "label": "Multi-Level Factorisation Net.      Reference:         Chang et al. Multi-Level", "file_type": "rationale", "source_file": "backend/references/sn-reid/torchreid/models/mlfn.py", "source_location": "L99"}, {"id": "mlfn_rationale_245", "label": "Initializes model with pretrained weights.          Layers that don't match with", "file_type": "rationale", "source_file": "backend/references/sn-reid/torchreid/models/mlfn.py", "source_location": "L245"}], "edges": [{"source": "backend_references_sn_reid_torchreid_models_mlfn_py", "target": "torch", "relation": "imports", "confidence": "EXTRACTED", "source_file": "backend/references/sn-reid/torchreid/models/mlfn.py", "source_location": "L2", "weight": 1.0}, {"source": "backend_references_sn_reid_torchreid_models_mlfn_py", "target": "torch_utils_model_zoo", "relation": "imports", "confidence": "EXTRACTED", "source_file": "backend/references/sn-reid/torchreid/models/mlfn.py", "source_location": "L3", "weight": 1.0}, {"source": "backend_references_sn_reid_torchreid_models_mlfn_py", "target": "torch", "relation": "imports_from", "confidence": "EXTRACTED", "source_file": "backend/references/sn-reid/torchreid/models/mlfn.py", "source_location": "L4", "weight": 1.0}, {"source": "backend_references_sn_reid_torchreid_models_mlfn_py", "target": "torch_nn", "relation": "imports_from", "confidence": "EXTRACTED", "source_file": "backend/references/sn-reid/torchreid/models/mlfn.py", "source_location": "L5", "weight": 1.0}, {"source": "backend_references_sn_reid_torchreid_models_mlfn_py", "target": "mlfn_mlfnblock", "relation": "contains", "confidence": "EXTRACTED", "source_file": "backend/references/sn-reid/torchreid/models/mlfn.py", "source_location": "L16", "weight": 1.0}, {"source": "mlfn_mlfnblock", "target": "mlfn_mlfnblock_init", "relation": "method", "confidence": "EXTRACTED", "source_file": "backend/references/sn-reid/torchreid/models/mlfn.py", "source_location": "L18", "weight": 1.0}, {"source": "mlfn_mlfnblock", "target": "mlfn_mlfnblock_forward", "relation": "method", "confidence": "EXTRACTED", "source_file": "backend/references/sn-reid/torchreid/models/mlfn.py", "source_location": "L64", "weight": 1.0}, {"source": "backend_references_sn_reid_torchreid_models_mlfn_py", "target": "mlfn_mlfn", "relation": "contains", "confidence": "EXTRACTED", "source_file": "backend/references/sn-reid/torchreid/models/mlfn.py", "source_location": "L98", "weight": 1.0}, {"source": "mlfn_mlfn", "target": "mlfn_mlfn_init", "relation": "method", "confidence": "EXTRACTED", "source_file": "backend/references/sn-reid/torchreid/models/mlfn.py", "source_location": "L109", "weight": 1.0}, {"source": "mlfn_mlfn", "target": "mlfn_mlfn_init_params", "relation": "method", "confidence": "EXTRACTED", "source_file": "backend/references/sn-reid/torchreid/models/mlfn.py", "source_location": "L196", "weight": 1.0}, {"source": "mlfn_mlfn", "target": "mlfn_mlfn_forward", "relation": "method", "confidence": "EXTRACTED", "source_file": "backend/references/sn-reid/torchreid/models/mlfn.py", "source_location": "L212", "weight": 1.0}, {"source": "backend_references_sn_reid_torchreid_models_mlfn_py", "target": "mlfn_init_pretrained_weights", "relation": "contains", "confidence": "EXTRACTED", "source_file": "backend/references/sn-reid/torchreid/models/mlfn.py", "source_location": "L244", "weight": 1.0}, {"source": "backend_references_sn_reid_torchreid_models_mlfn_py", "target": "mlfn_mlfn", "relation": "contains", "confidence": "EXTRACTED", "source_file": "backend/references/sn-reid/torchreid/models/mlfn.py", "source_location": "L260", "weight": 1.0}, {"source": "mlfn_mlfnblock_init", "target": "mlfn_mlfn_init", "relation": "calls", "confidence": "EXTRACTED", "source_file": "backend/references/sn-reid/torchreid/models/mlfn.py", "source_location": "L21", "weight": 1.0}, {"source": "mlfn_mlfn_init", "target": "mlfn_mlfnblock", "relation": "calls", "confidence": "EXTRACTED", "source_file": "backend/references/sn-reid/torchreid/models/mlfn.py", "source_location": "L131", "weight": 1.0}, {"source": "mlfn_mlfn_init", "target": "mlfn_mlfn_init_params", "relation": "calls", "confidence": "EXTRACTED", "source_file": "backend/references/sn-reid/torchreid/models/mlfn.py", "source_location": "L194", "weight": 1.0}, {"source": "mlfn_rationale_99", "target": "mlfn_mlfn", "relation": "rationale_for", "confidence": "EXTRACTED", "source_file": "backend/references/sn-reid/torchreid/models/mlfn.py", "source_location": "L99", "weight": 1.0}, {"source": "mlfn_rationale_245", "target": "mlfn_init_pretrained_weights", "relation": "rationale_for", "confidence": "EXTRACTED", "source_file": "backend/references/sn-reid/torchreid/models/mlfn.py", "source_location": "L245", "weight": 1.0}], "raw_calls": [{"caller_nid": "mlfn_mlfnblock_init", "callee": "super", "source_file": "backend/references/sn-reid/torchreid/models/mlfn.py", "source_location": "L21"}, {"caller_nid": "mlfn_mlfnblock_init", "callee": "Conv2d", "source_file": "backend/references/sn-reid/torchreid/models/mlfn.py", "source_location": "L26"}, {"caller_nid": "mlfn_mlfnblock_init", "callee": "BatchNorm2d", "source_file": "backend/references/sn-reid/torchreid/models/mlfn.py", "source_location": "L27"}, {"caller_nid": "mlfn_mlfnblock_init", "callee": "Conv2d", "source_file": "backend/references/sn-reid/torchreid/models/mlfn.py", "source_location": "L28"}, {"caller_nid": "mlfn_mlfnblock_init", "callee": "BatchNorm2d", "source_file": "backend/references/sn-reid/torchreid/models/mlfn.py", "source_location": "L37"}, {"caller_nid": "mlfn_mlfnblock_init", "callee": "Conv2d", "source_file": "backend/references/sn-reid/torchreid/models/mlfn.py", "source_location": "L38"}, {"caller_nid": "mlfn_mlfnblock_init", "callee": "BatchNorm2d", "source_file": "backend/references/sn-reid/torchreid/models/mlfn.py", "source_location": "L39"}, {"caller_nid": "mlfn_mlfnblock_init", "callee": "Sequential", "source_file": "backend/references/sn-reid/torchreid/models/mlfn.py", "source_location": "L42"}, {"caller_nid": "mlfn_mlfnblock_init", "callee": "AdaptiveAvgPool2d", "source_file": "backend/references/sn-reid/torchreid/models/mlfn.py", "source_location": "L43"}, {"caller_nid": "mlfn_mlfnblock_init", "callee": "Conv2d", "source_file": "backend/references/sn-reid/torchreid/models/mlfn.py", "source_location": "L44"}, {"caller_nid": "mlfn_mlfnblock_init", "callee": "BatchNorm2d", "source_file": "backend/references/sn-reid/torchreid/models/mlfn.py", "source_location": "L45"}, {"caller_nid": "mlfn_mlfnblock_init", "callee": "ReLU", "source_file": "backend/references/sn-reid/torchreid/models/mlfn.py", "source_location": "L46"}, {"caller_nid": "mlfn_mlfnblock_init", "callee": "Conv2d", "source_file": "backend/references/sn-reid/torchreid/models/mlfn.py", "source_location": "L47"}, {"caller_nid": "mlfn_mlfnblock_init", "callee": "BatchNorm2d", "source_file": "backend/references/sn-reid/torchreid/models/mlfn.py", "source_location": "L48"}, {"caller_nid": "mlfn_mlfnblock_init", "callee": "ReLU", "source_file": "backend/references/sn-reid/torchreid/models/mlfn.py", "source_location": "L49"}, {"caller_nid": "mlfn_mlfnblock_init", "callee": "Conv2d", "source_file": "backend/references/sn-reid/torchreid/models/mlfn.py", "source_location": "L50"}, {"caller_nid": "mlfn_mlfnblock_init", "callee": "BatchNorm2d", "source_file": "backend/references/sn-reid/torchreid/models/mlfn.py", "source_location": "L51"}, {"caller_nid": "mlfn_mlfnblock_init", "callee": "Sigmoid", "source_file": "backend/references/sn-reid/torchreid/models/mlfn.py", "source_location": "L52"}, {"caller_nid": "mlfn_mlfnblock_init", "callee": "Sequential", "source_file": "backend/references/sn-reid/torchreid/models/mlfn.py", "source_location": "L57"}, {"caller_nid": "mlfn_mlfnblock_init", "callee": "Conv2d", "source_file": "backend/references/sn-reid/torchreid/models/mlfn.py", "source_location": "L58"}, {"caller_nid": "mlfn_mlfnblock_init", "callee": "BatchNorm2d", "source_file": "backend/references/sn-reid/torchreid/models/mlfn.py", "source_location": "L61"}, {"caller_nid": "mlfn_mlfnblock_forward", "callee": "fsm", "source_file": "backend/references/sn-reid/torchreid/models/mlfn.py", "source_location": "L66"}, {"caller_nid": "mlfn_mlfnblock_forward", "callee": "fm_conv1", "source_file": "backend/references/sn-reid/torchreid/models/mlfn.py", "source_location": "L69"}, {"caller_nid": "mlfn_mlfnblock_forward", "callee": "fm_bn1", "source_file": "backend/references/sn-reid/torchreid/models/mlfn.py", "source_location": "L70"}, {"caller_nid": "mlfn_mlfnblock_forward", "callee": "relu", "source_file": "backend/references/sn-reid/torchreid/models/mlfn.py", "source_location": "L71"}, {"caller_nid": "mlfn_mlfnblock_forward", "callee": "fm_conv2", "source_file": "backend/references/sn-reid/torchreid/models/mlfn.py", "source_location": "L74"}, {"caller_nid": "mlfn_mlfnblock_forward", "callee": "fm_bn2", "source_file": "backend/references/sn-reid/torchreid/models/mlfn.py", "source_location": "L75"}, {"caller_nid": "mlfn_mlfnblock_forward", "callee": "relu", "source_file": "backend/references/sn-reid/torchreid/models/mlfn.py", "source_location": "L76"}, {"caller_nid": "mlfn_mlfnblock_forward", "callee": "size", "source_file": "backend/references/sn-reid/torchreid/models/mlfn.py", "source_location": "L79"}, {"caller_nid": "mlfn_mlfnblock_forward", "callee": "size", "source_file": "backend/references/sn-reid/torchreid/models/mlfn.py", "source_location": "L79"}, {"caller_nid": "mlfn_mlfnblock_forward", "callee": "repeat", "source_file": "backend/references/sn-reid/torchreid/models/mlfn.py", "source_location": "L81"}, {"caller_nid": "mlfn_mlfnblock_forward", "callee": "view", "source_file": "backend/references/sn-reid/torchreid/models/mlfn.py", "source_location": "L82"}, {"caller_nid": "mlfn_mlfnblock_forward", "callee": "contiguous", "source_file": "backend/references/sn-reid/torchreid/models/mlfn.py", "source_location": "L83"}, {"caller_nid": "mlfn_mlfnblock_forward", "callee": "permute", "source_file": "backend/references/sn-reid/torchreid/models/mlfn.py", "source_location": "L83"}, {"caller_nid": "mlfn_mlfnblock_forward", "callee": "view", "source_file": "backend/references/sn-reid/torchreid/models/mlfn.py", "source_location": "L84"}, {"caller_nid": "mlfn_mlfnblock_forward", "callee": "fm_conv3", "source_file": "backend/references/sn-reid/torchreid/models/mlfn.py", "source_location": "L88"}, {"caller_nid": "mlfn_mlfnblock_forward", "callee": "fm_bn3", "source_file": "backend/references/sn-reid/torchreid/models/mlfn.py", "source_location": "L89"}, {"caller_nid": "mlfn_mlfnblock_forward", "callee": "relu", "source_file": "backend/references/sn-reid/torchreid/models/mlfn.py", "source_location": "L90"}, {"caller_nid": "mlfn_mlfnblock_forward", "callee": "downsample", "source_file": "backend/references/sn-reid/torchreid/models/mlfn.py", "source_location": "L93"}, {"caller_nid": "mlfn_mlfnblock_forward", "callee": "relu", "source_file": "backend/references/sn-reid/torchreid/models/mlfn.py", "source_location": "L95"}, {"caller_nid": "mlfn_mlfn_init", "callee": "super", "source_file": "backend/references/sn-reid/torchreid/models/mlfn.py", "source_location": "L118"}, {"caller_nid": "mlfn_mlfn_init", "callee": "Conv2d", "source_file": "backend/references/sn-reid/torchreid/models/mlfn.py", "source_location": "L123"}, {"caller_nid": "mlfn_mlfn_init", "callee": "BatchNorm2d", "source_file": "backend/references/sn-reid/torchreid/models/mlfn.py", "source_location": "L124"}, {"caller_nid": "mlfn_mlfn_init", "callee": "MaxPool2d", "source_file": "backend/references/sn-reid/torchreid/models/mlfn.py", "source_location": "L125"}, {"caller_nid": "mlfn_mlfn_init", "callee": "ModuleList", "source_file": "backend/references/sn-reid/torchreid/models/mlfn.py", "source_location": "L128"}, {"caller_nid": "mlfn_mlfn_init", "callee": "AdaptiveAvgPool2d", "source_file": "backend/references/sn-reid/torchreid/models/mlfn.py", "source_location": "L178"}, {"caller_nid": "mlfn_mlfn_init", "callee": "Sequential", "source_file": "backend/references/sn-reid/torchreid/models/mlfn.py", "source_location": "L181"}, {"caller_nid": "mlfn_mlfn_init", "callee": "Conv2d", "source_file": "backend/references/sn-reid/torchreid/models/mlfn.py", "source_location": "L182"}, {"caller_nid": "mlfn_mlfn_init", "callee": "BatchNorm2d", "source_file": "backend/references/sn-reid/torchreid/models/mlfn.py", "source_location": "L183"}, {"caller_nid": "mlfn_mlfn_init", "callee": "ReLU", "source_file": "backend/references/sn-reid/torchreid/models/mlfn.py", "source_location": "L184"}, {"caller_nid": "mlfn_mlfn_init", "callee": "Sequential", "source_file": "backend/references/sn-reid/torchreid/models/mlfn.py", "source_location": "L186"}, {"caller_nid": "mlfn_mlfn_init", "callee": "Conv2d", "source_file": "backend/references/sn-reid/torchreid/models/mlfn.py", "source_location": "L187"}, {"caller_nid": "mlfn_mlfn_init", "callee": "BatchNorm2d", "source_file": "backend/references/sn-reid/torchreid/models/mlfn.py", "source_location": "L188"}, {"caller_nid": "mlfn_mlfn_init", "callee": "ReLU", "source_file": "backend/references/sn-reid/torchreid/models/mlfn.py", "source_location": "L189"}, {"caller_nid": "mlfn_mlfn_init", "callee": "Linear", "source_file": "backend/references/sn-reid/torchreid/models/mlfn.py", "source_location": "L192"}, {"caller_nid": "mlfn_mlfn_init_params", "callee": "modules", "source_file": "backend/references/sn-reid/torchreid/models/mlfn.py", "source_location": "L197"}, {"caller_nid": "mlfn_mlfn_init_params", "callee": "isinstance", "source_file": "backend/references/sn-reid/torchreid/models/mlfn.py", "source_location": "L198"}, {"caller_nid": "mlfn_mlfn_init_params", "callee": "kaiming_normal_", "source_file": "backend/references/sn-reid/torchreid/models/mlfn.py", "source_location": "L199"}, {"caller_nid": "mlfn_mlfn_init_params", "callee": "constant_", "source_file": "backend/references/sn-reid/torchreid/models/mlfn.py", "source_location": "L203"}, {"caller_nid": "mlfn_mlfn_init_params", "callee": "isinstance", "source_file": "backend/references/sn-reid/torchreid/models/mlfn.py", "source_location": "L204"}, {"caller_nid": "mlfn_mlfn_init_params", "callee": "constant_", "source_file": "backend/references/sn-reid/torchreid/models/mlfn.py", "source_location": "L205"}, {"caller_nid": "mlfn_mlfn_init_params", "callee": "constant_", "source_file": "backend/references/sn-reid/torchreid/models/mlfn.py", "source_location": "L206"}, {"caller_nid": "mlfn_mlfn_init_params", "callee": "isinstance", "source_file": "backend/references/sn-reid/torchreid/models/mlfn.py", "source_location": "L207"}, {"caller_nid": "mlfn_mlfn_init_params", "callee": "normal_", "source_file": "backend/references/sn-reid/torchreid/models/mlfn.py", "source_location": "L208"}, {"caller_nid": "mlfn_mlfn_init_params", "callee": "constant_", "source_file": "backend/references/sn-reid/torchreid/models/mlfn.py", "source_location": "L210"}, {"caller_nid": "mlfn_mlfn_forward", "callee": "conv1", "source_file": "backend/references/sn-reid/torchreid/models/mlfn.py", "source_location": "L213"}, {"caller_nid": "mlfn_mlfn_forward", "callee": "bn1", "source_file": "backend/references/sn-reid/torchreid/models/mlfn.py", "source_location": "L214"}, {"caller_nid": "mlfn_mlfn_forward", "callee": "relu", "source_file": "backend/references/sn-reid/torchreid/models/mlfn.py", "source_location": "L215"}, {"caller_nid": "mlfn_mlfn_forward", "callee": "maxpool", "source_file": "backend/references/sn-reid/torchreid/models/mlfn.py", "source_location": "L216"}, {"caller_nid": "mlfn_mlfn_forward", "callee": "block", "source_file": "backend/references/sn-reid/torchreid/models/mlfn.py", "source_location": "L220"}, {"caller_nid": "mlfn_mlfn_forward", "callee": "append", "source_file": "backend/references/sn-reid/torchreid/models/mlfn.py", "source_location": "L221"}, {"caller_nid": "mlfn_mlfn_forward", "callee": "cat", "source_file": "backend/references/sn-reid/torchreid/models/mlfn.py", "source_location": "L222"}, {"caller_nid": "mlfn_mlfn_forward", "callee": "global_avgpool", "source_file": "backend/references/sn-reid/torchreid/models/mlfn.py", "source_location": "L224"}, {"caller_nid": "mlfn_mlfn_forward", "callee": "fc_x", "source_file": "backend/references/sn-reid/torchreid/models/mlfn.py", "source_location": "L225"}, {"caller_nid": "mlfn_mlfn_forward", "callee": "fc_s", "source_file": "backend/references/sn-reid/torchreid/models/mlfn.py", "source_location": "L226"}, {"caller_nid": "mlfn_mlfn_forward", "callee": "view", "source_file": "backend/references/sn-reid/torchreid/models/mlfn.py", "source_location": "L229"}, {"caller_nid": "mlfn_mlfn_forward", "callee": "size", "source_file": "backend/references/sn-reid/torchreid/models/mlfn.py", "source_location": "L229"}, {"caller_nid": "mlfn_mlfn_forward", "callee": "classifier", "source_file": "backend/references/sn-reid/torchreid/models/mlfn.py", "source_location": "L234"}, {"caller_nid": "mlfn_mlfn_forward", "callee": "KeyError", "source_file": "backend/references/sn-reid/torchreid/models/mlfn.py", "source_location": "L241"}, {"caller_nid": "mlfn_mlfn_forward", "callee": "format", "source_file": "backend/references/sn-reid/torchreid/models/mlfn.py", "source_location": "L241"}, {"caller_nid": "mlfn_init_pretrained_weights", "callee": "load_url", "source_file": "backend/references/sn-reid/torchreid/models/mlfn.py", "source_location": "L249"}, {"caller_nid": "mlfn_init_pretrained_weights", "callee": "state_dict", "source_file": "backend/references/sn-reid/torchreid/models/mlfn.py", "source_location": "L250"}, {"caller_nid": "mlfn_init_pretrained_weights", "callee": "items", "source_file": "backend/references/sn-reid/torchreid/models/mlfn.py", "source_location": "L253"}, {"caller_nid": "mlfn_init_pretrained_weights", "callee": "size", "source_file": "backend/references/sn-reid/torchreid/models/mlfn.py", "source_location": "L254"}, {"caller_nid": "mlfn_init_pretrained_weights", "callee": "size", "source_file": "backend/references/sn-reid/torchreid/models/mlfn.py", "source_location": "L254"}, {"caller_nid": "mlfn_init_pretrained_weights", "callee": "update", "source_file": "backend/references/sn-reid/torchreid/models/mlfn.py", "source_location": "L256"}, {"caller_nid": "mlfn_init_pretrained_weights", "callee": "load_state_dict", "source_file": "backend/references/sn-reid/torchreid/models/mlfn.py", "source_location": "L257"}, {"caller_nid": "mlfn_mlfn", "callee": "warn", "source_file": "backend/references/sn-reid/torchreid/models/mlfn.py", "source_location": "L265"}, {"caller_nid": "mlfn_mlfn", "callee": "format", "source_file": "backend/references/sn-reid/torchreid/models/mlfn.py", "source_location": "L266"}]}