{"nodes": [{"id": "pkg_losses_rst", "label": "torchreid.losses API reference", "file_type": "document", "source_file": "backend/references/sn-reid/docs/pkg/losses.rst", "source_location": null, "source_url": null, "captured_at": null, "author": null, "contributor": null}], "edges": [{"source": "pkg_losses_rst", "target": "pkg_metrics_rst", "relation": "conceptually_related_to", "confidence": "INFERRED", "confidence_score": 0.74, "source_file": "backend/references/sn-reid/docs/pkg/losses.rst", "source_location": null, "weight": 1.0}], "hyperedges": []}