{"nodes": [{"id": "backend_scripts_pipeline_core_track_teams_py", "label": "track_teams.py", "file_type": "code", "source_file": "backend/scripts/pipeline_core/track_teams.py", "source_location": "L1"}, {"id": "track_teams_role_to_payload", "label": "role_to_payload()", "file_type": "code", "source_file": "backend/scripts/pipeline_core/track_teams.py", "source_location": "L76"}, {"id": "track_teams_get_detection_color", "label": "get_detection_color()", "file_type": "code", "source_file": "backend/scripts/pipeline_core/track_teams.py", "source_location": "L89"}, {"id": "track_teams_get_detection_label", "label": "get_detection_label()", "file_type": "code", "source_file": "backend/scripts/pipeline_core/track_teams.py", "source_location": "L109"}, {"id": "track_teams_annotate_frame", "label": "annotate_frame()", "file_type": "code", "source_file": "backend/scripts/pipeline_core/track_teams.py", "source_location": "L130"}, {"id": "track_teams_main", "label": "main()", "file_type": "code", "source_file": "backend/scripts/pipeline_core/track_teams.py", "source_location": "L158"}, {"id": "track_teams_rationale_1", "label": "Team-aware tracking: YOLO + ByteTrack + team classification with soft lock and g", "file_type": "rationale", "source_file": "backend/scripts/pipeline_core/track_teams.py", "source_location": "L1"}, {"id": "track_teams_rationale_77", "label": "Map Global Draft role string to annotation payload: -1, (team_id, is_gk), or Non", "file_type": "rationale", "source_file": "backend/scripts/pipeline_core/track_teams.py", "source_location": "L77"}, {"id": "track_teams_rationale_93", "label": "Return BGR color: Team 0/1 for players, gray Unknown, yellow GK, default Ball/Re", "file_type": "rationale", "source_file": "backend/scripts/pipeline_core/track_teams.py", "source_location": "L93"}, {"id": "track_teams_rationale_114", "label": "Return label string; for players optionally include ID and team (e.g. ID:3 T0-GK", "file_type": "rationale", "source_file": "backend/scripts/pipeline_core/track_teams.py", "source_location": "L114"}, {"id": "track_teams_rationale_136", "label": "Draw boxes and labels with per-detection colors and labels.", "file_type": "rationale", "source_file": "backend/scripts/pipeline_core/track_teams.py", "source_location": "L136"}, {"id": "track_teams_rationale_159", "label": "Load model, run YOLO + ByteTrack + team classification, write output video.", "file_type": "rationale", "source_file": "backend/scripts/pipeline_core/track_teams.py", "source_location": "L159"}], "edges": [{"source": "backend_scripts_pipeline_core_track_teams_py", "target": "json", "relation": "imports", "confidence": "EXTRACTED", "source_file": "backend/scripts/pipeline_core/track_teams.py", "source_location": "L13", "weight": 1.0}, {"source": "backend_scripts_pipeline_core_track_teams_py", "target": "logging", "relation": "imports", "confidence": "EXTRACTED", "source_file": "backend/scripts/pipeline_core/track_teams.py", "source_location": "L14", "weight": 1.0}, {"source": "backend_scripts_pipeline_core_track_teams_py", "target": "math", "relation": "imports", "confidence": "EXTRACTED", "source_file": "backend/scripts/pipeline_core/track_teams.py", "source_location": "L15", "weight": 1.0}, {"source": "backend_scripts_pipeline_core_track_teams_py", "target": "os", "relation": "imports", "confidence": "EXTRACTED", "source_file": "backend/scripts/pipeline_core/track_teams.py", "source_location": "L16", "weight": 1.0}, {"source": "backend_scripts_pipeline_core_track_teams_py", "target": "sys", "relation": "imports", "confidence": "EXTRACTED", "source_file": "backend/scripts/pipeline_core/track_teams.py", "source_location": "L17", "weight": 1.0}, {"source": "backend_scripts_pipeline_core_track_teams_py", "target": "collections", "relation": "imports_from", "confidence": "EXTRACTED", "source_file": "backend/scripts/pipeline_core/track_teams.py", "source_location": "L18", "weight": 1.0}, {"source": "backend_scripts_pipeline_core_track_teams_py", "target": "pathlib", "relation": "imports_from", "confidence": "EXTRACTED", "source_file": "backend/scripts/pipeline_core/track_teams.py", "source_location": "L19", "weight": 1.0}, {"source": "backend_scripts_pipeline_core_track_teams_py", "target": "typing", "relation": "imports_from", "confidence": "EXTRACTED", "source_file": "backend/scripts/pipeline_core/track_teams.py", "source_location": "L20", "weight": 1.0}, {"source": "backend_scripts_pipeline_core_track_teams_py", "target": "cv2", "relation": "imports", "confidence": "EXTRACTED", "source_file": "backend/scripts/pipeline_core/track_teams.py", "source_location": "L22", "weight": 1.0}, {"source": "backend_scripts_pipeline_core_track_teams_py", "target": "numpy", "relation": "imports", "confidence": "EXTRACTED", "source_file": "backend/scripts/pipeline_core/track_teams.py", "source_location": "L23", "weight": 1.0}, {"source": "backend_scripts_pipeline_core_track_teams_py", "target": "supervision", "relation": "imports", "confidence": "EXTRACTED", "source_file": "backend/scripts/pipeline_core/track_teams.py", "source_location": "L24", "weight": 1.0}, {"source": "backend_scripts_pipeline_core_track_teams_py", "target": "sklearn_cluster", "relation": "imports_from", "confidence": "EXTRACTED", "source_file": "backend/scripts/pipeline_core/track_teams.py", "source_location": "L25", "weight": 1.0}, {"source": "backend_scripts_pipeline_core_track_teams_py", "target": "ultralytics", "relation": "imports_from", "confidence": "EXTRACTED", "source_file": "backend/scripts/pipeline_core/track_teams.py", "source_location": "L26", "weight": 1.0}, {"source": "backend_scripts_pipeline_core_track_teams_py", "target": "services_pipeline_paths", "relation": "imports_from", "confidence": "EXTRACTED", "source_file": "backend/scripts/pipeline_core/track_teams.py", "source_location": "L40", "weight": 1.0}, {"source": "backend_scripts_pipeline_core_track_teams_py", "target": "services_homography_provider", "relation": "imports_from", "confidence": "EXTRACTED", "source_file": "backend/scripts/pipeline_core/track_teams.py", "source_location": "L45", "weight": 1.0}, {"source": "backend_scripts_pipeline_core_track_teams_py", "target": "backend_scripts_pipeline_core_track_teams_constants_py", "relation": "imports_from", "confidence": "EXTRACTED", "source_file": "backend/scripts/pipeline_core/track_teams.py", "source_location": "L47", "weight": 1.0}, {"source": "backend_scripts_pipeline_core_track_teams_py", "target": "backend_scripts_pipeline_core_track_teams_reid_hybrid_py", "relation": "imports_from", "confidence": "EXTRACTED", "source_file": "backend/scripts/pipeline_core/track_teams.py", "source_location": "L65", "weight": 1.0}, {"source": "backend_scripts_pipeline_core_track_teams_py", "target": "backend_scripts_pipeline_core_team_classifier_py", "relation": "imports_from", "confidence": "EXTRACTED", "source_file": "backend/scripts/pipeline_core/track_teams.py", "source_location": "L73", "weight": 1.0}, {"source": "backend_scripts_pipeline_core_track_teams_py", "target": "backend_scripts_pipeline_core_tactical_radar_py", "relation": "imports_from", "confidence": "EXTRACTED", "source_file": "backend/scripts/pipeline_core/track_teams.py", "source_location": "L74", "weight": 1.0}, {"source": "backend_scripts_pipeline_core_track_teams_py", "target": "track_teams_role_to_payload", "relation": "contains", "confidence": "EXTRACTED", "source_file": "backend/scripts/pipeline_core/track_teams.py", "source_location": "L76", "weight": 1.0}, {"source": "backend_scripts_pipeline_core_track_teams_py", "target": "track_teams_get_detection_color", "relation": "contains", "confidence": "EXTRACTED", "source_file": "backend/scripts/pipeline_core/track_teams.py", "source_location": "L89", "weight": 1.0}, {"source": "backend_scripts_pipeline_core_track_teams_py", "target": "track_teams_get_detection_label", "relation": "contains", "confidence": "EXTRACTED", "source_file": "backend/scripts/pipeline_core/track_teams.py", "source_location": "L109", "weight": 1.0}, {"source": "backend_scripts_pipeline_core_track_teams_py", "target": "track_teams_annotate_frame", "relation": "contains", "confidence": "EXTRACTED", "source_file": "backend/scripts/pipeline_core/track_teams.py", "source_location": "L130", "weight": 1.0}, {"source": "backend_scripts_pipeline_core_track_teams_py", "target": "track_teams_main", "relation": "contains", "confidence": "EXTRACTED", "source_file": "backend/scripts/pipeline_core/track_teams.py", "source_location": "L158", "weight": 1.0}, {"source": "track_teams_annotate_frame", "target": "track_teams_get_detection_color", "relation": "calls", "confidence": "EXTRACTED", "source_file": "backend/scripts/pipeline_core/track_teams.py", "source_location": "L138", "weight": 1.0}, {"source": "track_teams_annotate_frame", "target": "track_teams_get_detection_label", "relation": "calls", "confidence": "EXTRACTED", "source_file": "backend/scripts/pipeline_core/track_teams.py", "source_location": "L141", "weight": 1.0}, {"source": "track_teams_main", "target": "track_teams_role_to_payload", "relation": "calls", "confidence": "EXTRACTED", "source_file": "backend/scripts/pipeline_core/track_teams.py", "source_location": "L259", "weight": 1.0}, {"source": "track_teams_main", "target": "track_teams_annotate_frame", "relation": "calls", "confidence": "EXTRACTED", "source_file": "backend/scripts/pipeline_core/track_teams.py", "source_location": "L261", "weight": 1.0}, {"source": "track_teams_rationale_1", "target": "backend_scripts_pipeline_core_track_teams_py", "relation": "rationale_for", "confidence": "EXTRACTED", "source_file": "backend/scripts/pipeline_core/track_teams.py", "source_location": "L1", "weight": 1.0}, {"source": "track_teams_rationale_77", "target": "track_teams_role_to_payload", "relation": "rationale_for", "confidence": "EXTRACTED", "source_file": "backend/scripts/pipeline_core/track_teams.py", "source_location": "L77", "weight": 1.0}, {"source": "track_teams_rationale_93", "target": "track_teams_get_detection_color", "relation": "rationale_for", "confidence": "EXTRACTED", "source_file": "backend/scripts/pipeline_core/track_teams.py", "source_location": "L93", "weight": 1.0}, {"source": "track_teams_rationale_114", "target": "track_teams_get_detection_label", "relation": "rationale_for", "confidence": "EXTRACTED", "source_file": "backend/scripts/pipeline_core/track_teams.py", "source_location": "L114", "weight": 1.0}, {"source": "track_teams_rationale_136", "target": "track_teams_annotate_frame", "relation": "rationale_for", "confidence": "EXTRACTED", "source_file": "backend/scripts/pipeline_core/track_teams.py", "source_location": "L136", "weight": 1.0}, {"source": "track_teams_rationale_159", "target": "track_teams_main", "relation": "rationale_for", "confidence": "EXTRACTED", "source_file": "backend/scripts/pipeline_core/track_teams.py", "source_location": "L159", "weight": 1.0}], "raw_calls": [{"caller_nid": "track_teams_get_detection_color", "callee": "isinstance", "source_file": "backend/scripts/pipeline_core/track_teams.py", "source_location": "L97"}, {"caller_nid": "track_teams_get_detection_color", "callee": "get", "source_file": "backend/scripts/pipeline_core/track_teams.py", "source_location": "L101"}, {"caller_nid": "track_teams_get_detection_label", "callee": "isinstance", "source_file": "backend/scripts/pipeline_core/track_teams.py", "source_location": "L118"}, {"caller_nid": "track_teams_annotate_frame", "callee": "len", "source_file": "backend/scripts/pipeline_core/track_teams.py", "source_location": "L137"}, {"caller_nid": "track_teams_annotate_frame", "callee": "int", "source_file": "backend/scripts/pipeline_core/track_teams.py", "source_location": "L138"}, {"caller_nid": "track_teams_annotate_frame", "callee": "range", "source_file": "backend/scripts/pipeline_core/track_teams.py", "source_location": "L138"}, {"caller_nid": "track_teams_annotate_frame", "callee": "int", "source_file": "backend/scripts/pipeline_core/track_teams.py", "source_location": "L139"}, {"caller_nid": "track_teams_annotate_frame", "callee": "len", "source_file": "backend/scripts/pipeline_core/track_teams.py", "source_location": "L139"}, {"caller_nid": "track_teams_annotate_frame", "callee": "int", "source_file": "backend/scripts/pipeline_core/track_teams.py", "source_location": "L141"}, {"caller_nid": "track_teams_annotate_frame", "callee": "tid_at", "source_file": "backend/scripts/pipeline_core/track_teams.py", "source_location": "L141"}, {"caller_nid": "track_teams_annotate_frame", "callee": "range", "source_file": "backend/scripts/pipeline_core/track_teams.py", "source_location": "L142"}, {"caller_nid": "track_teams_annotate_frame", "callee": "copy", "source_file": "backend/scripts/pipeline_core/track_teams.py", "source_location": "L146"}, {"caller_nid": "track_teams_annotate_frame", "callee": "range", "source_file": "backend/scripts/pipeline_core/track_teams.py", "source_location": "L147"}, {"caller_nid": "track_teams_annotate_frame", "callee": "astype", "source_file": "backend/scripts/pipeline_core/track_teams.py", "source_location": "L148"}, {"caller_nid": "track_teams_annotate_frame", "callee": "rectangle", "source_file": "backend/scripts/pipeline_core/track_teams.py", "source_location": "L151"}, {"caller_nid": "track_teams_annotate_frame", "callee": "getTextSize", "source_file": "backend/scripts/pipeline_core/track_teams.py", "source_location": "L152"}, {"caller_nid": "track_teams_annotate_frame", "callee": "rectangle", "source_file": "backend/scripts/pipeline_core/track_teams.py", "source_location": "L153"}, {"caller_nid": "track_teams_annotate_frame", "callee": "putText", "source_file": "backend/scripts/pipeline_core/track_teams.py", "source_location": "L154"}, {"caller_nid": "track_teams_main", "callee": "is_file", "source_file": "backend/scripts/pipeline_core/track_teams.py", "source_location": "L160"}, {"caller_nid": "track_teams_main", "callee": "FileNotFoundError", "source_file": "backend/scripts/pipeline_core/track_teams.py", "source_location": "L161"}, {"caller_nid": "track_teams_main", "callee": "format_tracking_model_missing_reason", "source_file": "backend/scripts/pipeline_core/track_teams.py", "source_location": "L162"}, {"caller_nid": "track_teams_main", "callee": "exists", "source_file": "backend/scripts/pipeline_core/track_teams.py", "source_location": "L164"}, {"caller_nid": "track_teams_main", "callee": "FileNotFoundError", "source_file": "backend/scripts/pipeline_core/track_teams.py", "source_location": "L165"}, {"caller_nid": "track_teams_main", "callee": "info", "source_file": "backend/scripts/pipeline_core/track_teams.py", "source_location": "L167"}, {"caller_nid": "track_teams_main", "callee": "YOLO", "source_file": "backend/scripts/pipeline_core/track_teams.py", "source_location": "L168"}, {"caller_nid": "track_teams_main", "callee": "str", "source_file": "backend/scripts/pipeline_core/track_teams.py", "source_location": "L168"}, {"caller_nid": "track_teams_main", "callee": "ByteTrack", "source_file": "backend/scripts/pipeline_core/track_teams.py", "source_location": "L169"}, {"caller_nid": "track_teams_main", "callee": "BoxAnnotator", "source_file": "backend/scripts/pipeline_core/track_teams.py", "source_location": "L170"}, {"caller_nid": "track_teams_main", "callee": "LabelAnnotator", "source_file": "backend/scripts/pipeline_core/track_teams.py", "source_location": "L171"}, {"caller_nid": "track_teams_main", "callee": "TeamClassifier", "source_file": "backend/scripts/pipeline_core/track_teams.py", "source_location": "L172"}, {"caller_nid": "track_teams_main", "callee": "HybridIDHealer", "source_file": "backend/scripts/pipeline_core/track_teams.py", "source_location": "L173"}, {"caller_nid": "track_teams_main", "callee": "VideoCapture", "source_file": "backend/scripts/pipeline_core/track_teams.py", "source_location": "L175"}, {"caller_nid": "track_teams_main", "callee": "str", "source_file": "backend/scripts/pipeline_core/track_teams.py", "source_location": "L175"}, {"caller_nid": "track_teams_main", "callee": "isOpened", "source_file": "backend/scripts/pipeline_core/track_teams.py", "source_location": "L176"}, {"caller_nid": "track_teams_main", "callee": "RuntimeError", "source_file": "backend/scripts/pipeline_core/track_teams.py", "source_location": "L177"}, {"caller_nid": "track_teams_main", "callee": "int", "source_file": "backend/scripts/pipeline_core/track_teams.py", "source_location": "L179"}, {"caller_nid": "track_teams_main", "callee": "get", "source_file": "backend/scripts/pipeline_core/track_teams.py", "source_location": "L179"}, {"caller_nid": "track_teams_main", "callee": "int", "source_file": "backend/scripts/pipeline_core/track_teams.py", "source_location": "L180"}, {"caller_nid": "track_teams_main", "callee": "get", "source_file": "backend/scripts/pipeline_core/track_teams.py", "source_location": "L180"}, {"caller_nid": "track_teams_main", "callee": "int", "source_file": "backend/scripts/pipeline_core/track_teams.py", "source_location": "L181"}, {"caller_nid": "track_teams_main", "callee": "get", "source_file": "backend/scripts/pipeline_core/track_teams.py", "source_location": "L181"}, {"caller_nid": "track_teams_main", "callee": "int", "source_file": "backend/scripts/pipeline_core/track_teams.py", "source_location": "L182"}, {"caller_nid": "track_teams_main", "callee": "get", "source_file": "backend/scripts/pipeline_core/track_teams.py", "source_location": "L182"}, {"caller_nid": "track_teams_main", "callee": "info", "source_file": "backend/scripts/pipeline_core/track_teams.py", "source_location": "L183"}, {"caller_nid": "track_teams_main", "callee": "ensure_homography_json", "source_file": "backend/scripts/pipeline_core/track_teams.py", "source_location": "L185"}, {"caller_nid": "track_teams_main", "callee": "default_homography_provider", "source_file": "backend/scripts/pipeline_core/track_teams.py", "source_location": "L185"}, {"caller_nid": "track_teams_main", "callee": "TacticalRadar", "source_file": "backend/scripts/pipeline_core/track_teams.py", "source_location": "L186"}, {"caller_nid": "track_teams_main", "callee": "mkdir", "source_file": "backend/scripts/pipeline_core/track_teams.py", "source_location": "L188"}, {"caller_nid": "track_teams_main", "callee": "max", "source_file": "backend/scripts/pipeline_core/track_teams.py", "source_location": "L190"}, {"caller_nid": "track_teams_main", "callee": "VideoWriter_fourcc", "source_file": "backend/scripts/pipeline_core/track_teams.py", "source_location": "L192"}, {"caller_nid": "track_teams_main", "callee": "VideoWriter", "source_file": "backend/scripts/pipeline_core/track_teams.py", "source_location": "L193"}, {"caller_nid": "track_teams_main", "callee": "str", "source_file": "backend/scripts/pipeline_core/track_teams.py", "source_location": "L193"}, {"caller_nid": "track_teams_main", "callee": "isOpened", "source_file": "backend/scripts/pipeline_core/track_teams.py", "source_location": "L194"}, {"caller_nid": "track_teams_main", "callee": "release", "source_file": "backend/scripts/pipeline_core/track_teams.py", "source_location": "L195"}, {"caller_nid": "track_teams_main", "callee": "RuntimeError", "source_file": "backend/scripts/pipeline_core/track_teams.py", "source_location": "L196"}, {"caller_nid": "track_teams_main", "callee": "read", "source_file": "backend/scripts/pipeline_core/track_teams.py", "source_location": "L201"}, {"caller_nid": "track_teams_main", "callee": "model", "source_file": "backend/scripts/pipeline_core/track_teams.py", "source_location": "L206"}, {"caller_nid": "track_teams_main", "callee": "update_camera_angle", "source_file": "backend/scripts/pipeline_core/track_teams.py", "source_location": "L208"}, {"caller_nid": "track_teams_main", "callee": "draw_blank_pitch", "source_file": "backend/scripts/pipeline_core/track_teams.py", "source_location": "L209"}, {"caller_nid": "track_teams_main", "callee": "zeros", "source_file": "backend/scripts/pipeline_core/track_teams.py", "source_location": "L210"}, {"caller_nid": "track_teams_main", "callee": "write", "source_file": "backend/scripts/pipeline_core/track_teams.py", "source_location": "L213"}, {"caller_nid": "track_teams_main", "callee": "from_ultralytics", "source_file": "backend/scripts/pipeline_core/track_teams.py", "source_location": "L217"}, {"caller_nid": "track_teams_main", "callee": "update_with_detections", "source_file": "backend/scripts/pipeline_core/track_teams.py", "source_location": "L218"}, {"caller_nid": "track_teams_main", "callee": "update_camera_angle", "source_file": "backend/scripts/pipeline_core/track_teams.py", "source_location": "L220"}, {"caller_nid": "track_teams_main", "callee": "map_to_2d", "source_file": "backend/scripts/pipeline_core/track_teams.py", "source_location": "L222"}, {"caller_nid": "track_teams_main", "callee": "range", "source_file": "backend/scripts/pipeline_core/track_teams.py", "source_location": "L222"}, {"caller_nid": "track_teams_main", "callee": "len", "source_file": "backend/scripts/pipeline_core/track_teams.py", "source_location": "L222"}, {"caller_nid": "track_teams_main", "callee": "process_and_heal", "source_file": "backend/scripts/pipeline_core/track_teams.py", "source_location": "L225"}, {"caller_nid": "track_teams_main", "callee": "getattr", "source_file": "backend/scripts/pipeline_core/track_teams.py", "source_location": "L228"}, {"caller_nid": "track_teams_main", "callee": "range", "source_file": "backend/scripts/pipeline_core/track_teams.py", "source_location": "L230"}, {"caller_nid": "track_teams_main", "callee": "len", "source_file": "backend/scripts/pipeline_core/track_teams.py", "source_location": "L230"}, {"caller_nid": "track_teams_main", "callee": "len", "source_file": "backend/scripts/pipeline_core/track_teams.py", "source_location": "L232"}, {"caller_nid": "track_teams_main", "callee": "int", "source_file": "backend/scripts/pipeline_core/track_teams.py", "source_location": "L234"}, {"caller_nid": "track_teams_main", "callee": "append", "source_file": "backend/scripts/pipeline_core/track_teams.py", "source_location": "L236"}, {"caller_nid": "track_teams_main", "callee": "int", "source_file": "backend/scripts/pipeline_core/track_teams.py", "source_location": "L240"}, {"caller_nid": "track_teams_main", "callee": "predict_frame", "source_file": "backend/scripts/pipeline_core/track_teams.py", "source_location": "L246"}, {"caller_nid": "track_teams_main", "callee": "len", "source_file": "backend/scripts/pipeline_core/track_teams.py", "source_location": "L249"}, {"caller_nid": "track_teams_main", "callee": "enumerate", "source_file": "backend/scripts/pipeline_core/track_teams.py", "source_location": "L250"}, {"caller_nid": "track_teams_main", "callee": "get", "source_file": "backend/scripts/pipeline_core/track_teams.py", "source_location": "L255"}, {"caller_nid": "track_teams_main", "callee": "draw_blank_pitch", "source_file": "backend/scripts/pipeline_core/track_teams.py", "source_location": "L264"}, {"caller_nid": "track_teams_main", "callee": "get", "source_file": "backend/scripts/pipeline_core/track_teams.py", "source_location": "L270"}, {"caller_nid": "track_teams_main", "callee": "circle", "source_file": "backend/scripts/pipeline_core/track_teams.py", "source_location": "L284"}, {"caller_nid": "track_teams_main", "callee": "circle", "source_file": "backend/scripts/pipeline_core/track_teams.py", "source_location": "L285"}, {"caller_nid": "track_teams_main", "callee": "putText", "source_file": "backend/scripts/pipeline_core/track_teams.py", "source_location": "L286"}, {"caller_nid": "track_teams_main", "callee": "str", "source_file": "backend/scripts/pipeline_core/track_teams.py", "source_location": "L288"}, {"caller_nid": "track_teams_main", "callee": "zeros", "source_file": "backend/scripts/pipeline_core/track_teams.py", "source_location": "L297"}, {"caller_nid": "track_teams_main", "callee": "write", "source_file": "backend/scripts/pipeline_core/track_teams.py", "source_location": "L300"}, {"caller_nid": "track_teams_main", "callee": "info", "source_file": "backend/scripts/pipeline_core/track_teams.py", "source_location": "L303"}, {"caller_nid": "track_teams_main", "callee": "cleanup_ghost_ids", "source_file": "backend/scripts/pipeline_core/track_teams.py", "source_location": "L305"}, {"caller_nid": "track_teams_main", "callee": "info", "source_file": "backend/scripts/pipeline_core/track_teams.py", "source_location": "L306"}, {"caller_nid": "track_teams_main", "callee": "release", "source_file": "backend/scripts/pipeline_core/track_teams.py", "source_location": "L309"}, {"caller_nid": "track_teams_main", "callee": "release", "source_file": "backend/scripts/pipeline_core/track_teams.py", "source_location": "L310"}, {"caller_nid": "track_teams_main", "callee": "info", "source_file": "backend/scripts/pipeline_core/track_teams.py", "source_location": "L311"}]}